{
	"$schema": "http://schema.management.azure.com/schemas/2015-01-01/deploymentTemplate.json#",
	"contentVersion": "1.0.0.0",
	"parameters": {
		"factoryName": {
			"type": "string",
			"metadata": "Data Factory name",
			"defaultValue": "demolul22"
		}
	},
	"variables": {
		"factoryId": "[concat('Microsoft.DataFactory/factories/', parameters('factoryName'))]"
	},
	"resources": [
		{
			"name": "[concat(parameters('factoryName'), '/ifconditionoutput')]",
			"type": "Microsoft.DataFactory/factories/datasets",
			"apiVersion": "2018-06-01",
			"properties": {
				"linkedServiceName": {
					"referenceName": "LS_BLOB",
					"type": "LinkedServiceReference"
				},
				"parameters": {
					"outputfolderpath": {
						"type": "string"
					}
				},
				"annotations": [],
				"type": "Binary",
				"typeProperties": {
					"location": {
						"type": "AzureBlobStorageLocation",
						"folderPath": {
							"value": "@dataset().outputfolderpath",
							"type": "Expression"
						},
						"container": "ifcondition"
					}
				}
			},
			"dependsOn": []
		},
		{
			"name": "[concat(parameters('factoryName'), '/switchinput')]",
			"type": "Microsoft.DataFactory/factories/datasets",
			"apiVersion": "2018-06-01",
			"properties": {
				"linkedServiceName": {
					"referenceName": "LS_BLOB",
					"type": "LinkedServiceReference"
				},
				"annotations": [],
				"type": "Binary",
				"typeProperties": {
					"location": {
						"type": "AzureBlobStorageLocation",
						"folderPath": "input",
						"container": "switch"
					}
				}
			},
			"dependsOn": []
		},
		{
			"name": "[concat(parameters('factoryName'), '/switchoutput')]",
			"type": "Microsoft.DataFactory/factories/datasets",
			"apiVersion": "2018-06-01",
			"properties": {
				"linkedServiceName": {
					"referenceName": "LS_BLOB",
					"type": "LinkedServiceReference"
				},
				"parameters": {
					"outputfolder": {
						"type": "string"
					}
				},
				"annotations": [],
				"type": "Binary",
				"typeProperties": {
					"location": {
						"type": "AzureBlobStorageLocation",
						"folderPath": {
							"value": "@dataset().outputfolder",
							"type": "Expression"
						},
						"container": "switch"
					}
				}
			},
			"dependsOn": []
		},
		{
			"name": "[concat(parameters('factoryName'), '/switchsqloutput')]",
			"type": "Microsoft.DataFactory/factories/datasets",
			"apiVersion": "2018-06-01",
			"properties": {
				"linkedServiceName": {
					"referenceName": "LS_AZURESQL",
					"type": "LinkedServiceReference"
				},
				"parameters": {
					"DBname": {
						"type": "string"
					}
				},
				"annotations": [],
				"type": "AzureSqlTable",
				"schema": [],
				"typeProperties": {
					"schema": "dbo",
					"table": {
						"value": "@dataset().DBname",
						"type": "Expression"
					}
				}
			},
			"dependsOn": []
		},
		{
			"name": "[concat(parameters('factoryName'), '/triggerinputevent')]",
			"type": "Microsoft.DataFactory/factories/datasets",
			"apiVersion": "2018-06-01",
			"properties": {
				"linkedServiceName": {
					"referenceName": "LS_BLOB",
					"type": "LinkedServiceReference"
				},
				"parameters": {
					"folderPath": {
						"type": "string"
					},
					"fileName": {
						"type": "string"
					}
				},
				"annotations": [],
				"type": "Binary",
				"typeProperties": {
					"location": {
						"type": "AzureBlobStorageLocation",
						"fileName": {
							"value": "@dataset().fileName",
							"type": "Expression"
						},
						"folderPath": {
							"value": "@dataset().folderPath",
							"type": "Expression"
						},
						"container": "trigger"
					}
				}
			},
			"dependsOn": []
		},
		{
			"name": "[concat(parameters('factoryName'), '/triggerouput')]",
			"type": "Microsoft.DataFactory/factories/datasets",
			"apiVersion": "2018-06-01",
			"properties": {
				"linkedServiceName": {
					"referenceName": "LS_BLOB",
					"type": "LinkedServiceReference"
				},
				"annotations": [],
				"type": "Binary",
				"typeProperties": {
					"location": {
						"type": "AzureBlobStorageLocation",
						"folderPath": "scheduleouput",
						"container": "trigger"
					}
				}
			},
			"dependsOn": []
		},
		{
			"name": "[concat(parameters('factoryName'), '/tumblinginput')]",
			"type": "Microsoft.DataFactory/factories/datasets",
			"apiVersion": "2018-06-01",
			"properties": {
				"linkedServiceName": {
					"referenceName": "LS_AZURESQL",
					"type": "LinkedServiceReference"
				},
				"annotations": [],
				"type": "AzureSqlTable",
				"schema": [],
				"typeProperties": {}
			},
			"dependsOn": []
		},
		{
			"name": "[concat(parameters('factoryName'), '/tumblingoutput')]",
			"type": "Microsoft.DataFactory/factories/datasets",
			"apiVersion": "2018-06-01",
			"properties": {
				"linkedServiceName": {
					"referenceName": "LS_AZURESQL",
					"type": "LinkedServiceReference"
				},
				"annotations": [],
				"type": "AzureSqlTable",
				"schema": [
					{
						"name": "ID",
						"type": "int",
						"precision": 10
					},
					{
						"name": "CUSTNAME",
						"type": "varchar"
					},
					{
						"name": "TRXNDATE",
						"type": "varchar"
					}
				],
				"typeProperties": {
					"schema": "dbo",
					"table": "TUMBLING_OUTPUT"
				}
			},
			"dependsOn": []
		},
		{
			"name": "[concat(parameters('factoryName'), '/until_appendvarinput')]",
			"type": "Microsoft.DataFactory/factories/datasets",
			"apiVersion": "2018-06-01",
			"properties": {
				"linkedServiceName": {
					"referenceName": "LS_BLOB",
					"type": "LinkedServiceReference"
				},
				"annotations": [],
				"type": "DelimitedText",
				"typeProperties": {
					"location": {
						"type": "AzureBlobStorageLocation",
						"folderPath": "appendvariable",
						"container": "until"
					},
					"columnDelimiter": ",",
					"escapeChar": "\\",
					"firstRowAsHeader": true,
					"quoteChar": "\""
				},
				"schema": [
					{
						"name": "C.ID",
						"type": "String"
					},
					{
						"name": "FIRST_NAME",
						"type": "String"
					}
				]
			},
			"dependsOn": []
		},
		{
			"name": "[concat(parameters('factoryName'), '/until_cus1')]",
			"type": "Microsoft.DataFactory/factories/datasets",
			"apiVersion": "2018-06-01",
			"properties": {
				"linkedServiceName": {
					"referenceName": "LS_BLOB",
					"type": "LinkedServiceReference"
				},
				"annotations": [],
				"type": "DelimitedText",
				"typeProperties": {
					"location": {
						"type": "AzureBlobStorageLocation",
						"fileName": "Cus1.csv",
						"folderPath": "input",
						"container": "until"
					},
					"columnDelimiter": ",",
					"escapeChar": "\\",
					"firstRowAsHeader": true,
					"quoteChar": "\""
				},
				"schema": [
					{
						"name": "C.ID",
						"type": "String"
					},
					{
						"name": "FIRST_NAME",
						"type": "String"
					}
				]
			},
			"dependsOn": []
		},
		{
			"name": "[concat(parameters('factoryName'), '/untiloutput')]",
			"type": "Microsoft.DataFactory/factories/datasets",
			"apiVersion": "2018-06-01",
			"properties": {
				"linkedServiceName": {
					"referenceName": "LS_BLOB",
					"type": "LinkedServiceReference"
				},
				"annotations": [],
				"type": "DelimitedText",
				"typeProperties": {
					"location": {
						"type": "AzureBlobStorageLocation",
						"folderPath": "output",
						"container": "until"
					},
					"columnDelimiter": ",",
					"escapeChar": "\\",
					"firstRowAsHeader": true,
					"quoteChar": "\""
				},
				"schema": []
			},
			"dependsOn": []
		},
		{
			"name": "[concat(parameters('factoryName'), '/AppendVariable')]",
			"type": "Microsoft.DataFactory/factories/pipelines",
			"apiVersion": "2018-06-01",
			"properties": {
				"activities": [
					{
						"name": "List of Files",
						"type": "GetMetadata",
						"dependsOn": [],
						"policy": {
							"timeout": "7.00:00:00",
							"retry": 0,
							"retryIntervalInSeconds": 30,
							"secureOutput": false,
							"secureInput": false
						},
						"userProperties": [],
						"typeProperties": {
							"dataset": {
								"referenceName": "until_appendvarinput",
								"type": "DatasetReference",
								"parameters": {}
							},
							"fieldList": [
								"childItems"
							],
							"storeSettings": {
								"type": "AzureBlobStorageReadSettings",
								"recursive": true,
								"enablePartitionDiscovery": false
							},
							"formatSettings": {
								"type": "DelimitedTextReadSettings"
							}
						}
					},
					{
						"name": "ForEach1",
						"type": "ForEach",
						"dependsOn": [
							{
								"activity": "List of Files",
								"dependencyConditions": [
									"Succeeded"
								]
							}
						],
						"userProperties": [],
						"typeProperties": {
							"items": {
								"value": "@activity('List of Files').output.childItems",
								"type": "Expression"
							},
							"isSequential": true,
							"activities": [
								{
									"name": "Copy data1",
									"type": "Copy",
									"dependsOn": [],
									"policy": {
										"timeout": "7.00:00:00",
										"retry": 0,
										"retryIntervalInSeconds": 30,
										"secureOutput": false,
										"secureInput": false
									},
									"userProperties": [],
									"typeProperties": {
										"source": {
											"type": "DelimitedTextSource",
											"storeSettings": {
												"type": "AzureBlobStorageReadSettings",
												"recursive": true,
												"wildcardFolderPath": "appendvariable",
												"wildcardFileName": {
													"value": "@item().name",
													"type": "Expression"
												},
												"enablePartitionDiscovery": false
											},
											"formatSettings": {
												"type": "DelimitedTextReadSettings"
											}
										},
										"sink": {
											"type": "DelimitedTextSink",
											"storeSettings": {
												"type": "AzureBlobStorageWriteSettings"
											},
											"formatSettings": {
												"type": "DelimitedTextWriteSettings",
												"quoteAllText": true,
												"fileExtension": ".txt"
											}
										},
										"enableStaging": false,
										"translator": {
											"type": "TabularTranslator",
											"typeConversion": true,
											"typeConversionSettings": {
												"allowDataTruncation": true,
												"treatBooleanAsNumber": false
											}
										}
									},
									"inputs": [
										{
											"referenceName": "until_appendvarinput",
											"type": "DatasetReference",
											"parameters": {}
										}
									],
									"outputs": [
										{
											"referenceName": "untiloutput",
											"type": "DatasetReference",
											"parameters": {}
										}
									]
								},
								{
									"name": "Append variable1",
									"type": "AppendVariable",
									"dependsOn": [
										{
											"activity": "Copy data1",
											"dependencyConditions": [
												"Succeeded"
											]
										}
									],
									"userProperties": [],
									"typeProperties": {
										"variableName": "fileName_Copy",
										"value": {
											"value": "@item().name",
											"type": "Expression"
										}
									}
								},
								{
									"name": "Set variable1",
									"type": "SetVariable",
									"dependsOn": [
										{
											"activity": "Append variable1",
											"dependencyConditions": [
												"Succeeded"
											]
										}
									],
									"userProperties": [],
									"typeProperties": {
										"variableName": "fileName",
										"value": {
											"value": "@variables('fileName_Copy')",
											"type": "Expression"
										}
									}
								}
							]
						}
					}
				],
				"policy": {
					"elapsedTimeMetric": {},
					"cancelAfter": {}
				},
				"variables": {
					"fileName": {
						"type": "Array"
					},
					"fileName_Copy": {
						"type": "Array"
					}
				},
				"annotations": [],
				"lastPublishTime": "2022-08-20T06:22:43Z"
			},
			"dependsOn": [
				"[concat(variables('factoryId'), '/datasets/until_appendvarinput')]",
				"[concat(variables('factoryId'), '/datasets/untiloutput')]"
			]
		},
		{
			"name": "[concat(parameters('factoryName'), '/COPY_BLOB_SQL')]",
			"type": "Microsoft.DataFactory/factories/pipelines",
			"apiVersion": "2018-06-01",
			"properties": {
				"activities": [
					{
						"name": "Copy data1",
						"type": "Copy",
						"dependsOn": [],
						"policy": {
							"timeout": "7.00:00:00",
							"retry": 0,
							"retryIntervalInSeconds": 30,
							"secureOutput": false,
							"secureInput": false
						},
						"userProperties": [],
						"typeProperties": {
							"source": {
								"type": "DelimitedTextSource",
								"storeSettings": {
									"type": "AzureBlobStorageReadSettings",
									"recursive": true,
									"enablePartitionDiscovery": false
								},
								"formatSettings": {
									"type": "DelimitedTextReadSettings"
								}
							},
							"sink": {
								"type": "AzureSqlSink",
								"writeBehavior": "insert",
								"sqlWriterUseTableLock": false
							},
							"enableStaging": false,
							"translator": {
								"type": "TabularTranslator",
								"mappings": [
									{
										"source": {
											"name": "C.ID",
											"type": "String",
											"physicalType": "String"
										},
										"sink": {
											"name": "ID",
											"type": "Int32",
											"physicalType": "int"
										}
									},
									{
										"source": {
											"name": "FIRST_NAME",
											"type": "String",
											"physicalType": "String"
										},
										"sink": {
											"name": "NAME",
											"type": "String",
											"physicalType": "varchar"
										}
									}
								],
								"typeConversion": true,
								"typeConversionSettings": {
									"allowDataTruncation": true,
									"treatBooleanAsNumber": false
								}
							}
						},
						"inputs": [
							{
								"referenceName": "DYNAMIC_BLOB_INPUT",
								"type": "DatasetReference",
								"parameters": {
									"Filename": {
										"value": "@pipeline().parameters.InputFileName",
										"type": "Expression"
									}
								}
							}
						],
						"outputs": [
							{
								"referenceName": "SQL_DYNAMIC_OUTPUT",
								"type": "DatasetReference",
								"parameters": {
									"OutputDB": {
										"value": "@pipeline().parameters.OutputDBName",
										"type": "Expression"
									}
								}
							}
						]
					}
				],
				"policy": {
					"elapsedTimeMetric": {},
					"cancelAfter": {}
				},
				"parameters": {
					"InputFileName": {
						"type": "string"
					},
					"OutputDBName": {
						"type": "string"
					}
				},
				"annotations": [],
				"lastPublishTime": "2022-08-03T05:06:53Z"
			},
			"dependsOn": []
		},
		{
			"name": "[concat(parameters('factoryName'), '/COPY_DIFFERENTSCHEMA')]",
			"type": "Microsoft.DataFactory/factories/pipelines",
			"apiVersion": "2018-06-01",
			"properties": {
				"activities": [
					{
						"name": "Copy data1",
						"type": "Copy",
						"dependsOn": [],
						"policy": {
							"timeout": "7.00:00:00",
							"retry": 0,
							"retryIntervalInSeconds": 30,
							"secureOutput": false,
							"secureInput": false
						},
						"userProperties": [],
						"typeProperties": {
							"source": {
								"type": "AzureSqlSource",
								"sqlReaderQuery": "SELECT Id, NAME FROM DBO.TABLEC",
								"queryTimeout": "02:00:00",
								"partitionOption": "None"
							},
							"sink": {
								"type": "AzureSqlSink",
								"writeBehavior": "insert",
								"sqlWriterUseTableLock": false
							},
							"enableStaging": false,
							"translator": {
								"type": "TabularTranslator",
								"mappings": [
									{
										"source": {
											"name": "Id",
											"type": "Int32",
											"physicalType": "int"
										},
										"sink": {
											"name": "ID",
											"type": "Int32",
											"physicalType": "int"
										}
									},
									{
										"source": {
											"name": "NAME",
											"type": "String",
											"physicalType": "varchar"
										},
										"sink": {
											"name": "NAME",
											"type": "String",
											"physicalType": "varchar"
										}
									}
								],
								"typeConversion": true,
								"typeConversionSettings": {
									"allowDataTruncation": true,
									"treatBooleanAsNumber": false
								}
							}
						},
						"inputs": [
							{
								"referenceName": "SQLTABLEC",
								"type": "DatasetReference",
								"parameters": {}
							}
						],
						"outputs": [
							{
								"referenceName": "SQLTABLEB",
								"type": "DatasetReference",
								"parameters": {}
							}
						]
					}
				],
				"policy": {
					"elapsedTimeMetric": {},
					"cancelAfter": {}
				},
				"annotations": [],
				"lastPublishTime": "2022-08-03T05:06:53Z"
			},
			"dependsOn": []
		},
		{
			"name": "[concat(parameters('factoryName'), '/COPY_SQL_DIFFSCHEMA2')]",
			"type": "Microsoft.DataFactory/factories/pipelines",
			"apiVersion": "2018-06-01",
			"properties": {
				"activities": [
					{
						"name": "Copy data1",
						"type": "Copy",
						"dependsOn": [],
						"policy": {
							"timeout": "7.00:00:00",
							"retry": 0,
							"retryIntervalInSeconds": 30,
							"secureOutput": false,
							"secureInput": false
						},
						"userProperties": [],
						"typeProperties": {
							"source": {
								"type": "AzureSqlSource",
								"queryTimeout": "02:00:00",
								"partitionOption": "None"
							},
							"sink": {
								"type": "AzureSqlSink",
								"writeBehavior": "insert",
								"sqlWriterUseTableLock": false
							},
							"enableStaging": false,
							"translator": {
								"type": "TabularTranslator",
								"typeConversion": true,
								"typeConversionSettings": {
									"allowDataTruncation": true,
									"treatBooleanAsNumber": false
								}
							}
						},
						"inputs": [
							{
								"referenceName": "SQLTABLEB",
								"type": "DatasetReference",
								"parameters": {}
							}
						],
						"outputs": [
							{
								"referenceName": "SQLTABLEC",
								"type": "DatasetReference",
								"parameters": {}
							}
						]
					}
				],
				"policy": {
					"elapsedTimeMetric": {},
					"cancelAfter": {}
				},
				"annotations": [],
				"lastPublishTime": "2022-08-03T05:06:53Z"
			},
			"dependsOn": []
		},
		{
			"name": "[concat(parameters('factoryName'), '/COPY_SQL_DYNAMIC')]",
			"type": "Microsoft.DataFactory/factories/pipelines",
			"apiVersion": "2018-06-01",
			"properties": {
				"activities": [
					{
						"name": "Copy data1",
						"type": "Copy",
						"dependsOn": [],
						"policy": {
							"timeout": "7.00:00:00",
							"retry": 0,
							"retryIntervalInSeconds": 30,
							"secureOutput": false,
							"secureInput": false
						},
						"userProperties": [],
						"typeProperties": {
							"source": {
								"type": "AzureSqlSource",
								"queryTimeout": "02:00:00",
								"partitionOption": "None"
							},
							"sink": {
								"type": "AzureSqlSink",
								"writeBehavior": "insert",
								"sqlWriterUseTableLock": false
							},
							"enableStaging": false,
							"translator": {
								"type": "TabularTranslator",
								"typeConversion": true,
								"typeConversionSettings": {
									"allowDataTruncation": true,
									"treatBooleanAsNumber": false
								}
							}
						},
						"inputs": [
							{
								"referenceName": "SQL_DYNAMIC_INPUT",
								"type": "DatasetReference",
								"parameters": {
									"InputDB": {
										"value": "@pipeline().parameters.InputDB",
										"type": "Expression"
									}
								}
							}
						],
						"outputs": [
							{
								"referenceName": "SQL_DYNAMIC_OUTPUT",
								"type": "DatasetReference",
								"parameters": {
									"OutputDB": {
										"value": "@pipeline().parameters.OutputDB",
										"type": "Expression"
									}
								}
							}
						]
					}
				],
				"policy": {
					"elapsedTimeMetric": {},
					"cancelAfter": {}
				},
				"parameters": {
					"InputDB": {
						"type": "string"
					},
					"OutputDB": {
						"type": "string"
					}
				},
				"annotations": [],
				"lastPublishTime": "2022-08-03T05:06:53Z"
			},
			"dependsOn": []
		},
		{
			"name": "[concat(parameters('factoryName'), '/COPY_blob_ bytodaydate')]",
			"type": "Microsoft.DataFactory/factories/pipelines",
			"apiVersion": "2018-06-01",
			"properties": {
				"activities": [
					{
						"name": "Copy data1",
						"type": "Copy",
						"dependsOn": [],
						"policy": {
							"timeout": "7.00:00:00",
							"retry": 0,
							"retryIntervalInSeconds": 30,
							"secureOutput": false,
							"secureInput": false
						},
						"userProperties": [],
						"typeProperties": {
							"source": {
								"type": "DelimitedTextSource",
								"storeSettings": {
									"type": "AzureBlobStorageReadSettings",
									"recursive": false,
									"modifiedDatetimeStart": {
										"value": "@startOfDay(utcNow())",
										"type": "Expression"
									},
									"modifiedDatetimeEnd": "2022-08-04T23:00:00Z",
									"wildcardFileName": "*csv",
									"enablePartitionDiscovery": false
								},
								"formatSettings": {
									"type": "DelimitedTextReadSettings"
								}
							},
							"sink": {
								"type": "DelimitedTextSink",
								"storeSettings": {
									"type": "AzureBlobStorageWriteSettings"
								},
								"formatSettings": {
									"type": "DelimitedTextWriteSettings",
									"quoteAllText": true,
									"fileExtension": ".csv"
								}
							},
							"enableStaging": false,
							"translator": {
								"type": "TabularTranslator",
								"typeConversion": true,
								"typeConversionSettings": {
									"allowDataTruncation": true,
									"treatBooleanAsNumber": false
								}
							}
						},
						"inputs": [
							{
								"referenceName": "blobinput",
								"type": "DatasetReference",
								"parameters": {}
							}
						],
						"outputs": [
							{
								"referenceName": "bloboutput",
								"type": "DatasetReference",
								"parameters": {}
							}
						]
					}
				],
				"policy": {
					"elapsedTimeMetric": {},
					"cancelAfter": {}
				},
				"annotations": [],
				"lastPublishTime": "2022-08-04T04:57:43Z"
			},
			"dependsOn": []
		},
		{
			"name": "[concat(parameters('factoryName'), '/DELETE_DB')]",
			"type": "Microsoft.DataFactory/factories/pipelines",
			"apiVersion": "2018-06-01",
			"properties": {
				"activities": [
					{
						"name": "Copy data1",
						"type": "Copy",
						"dependsOn": [],
						"policy": {
							"timeout": "7.00:00:00",
							"retry": 0,
							"retryIntervalInSeconds": 30,
							"secureOutput": false,
							"secureInput": false
						},
						"userProperties": [],
						"typeProperties": {
							"source": {
								"type": "AzureSqlSource",
								"sqlReaderQuery": "TRUNCATE TABLE [DBO].[TESTA]\nSELECT * FROM  [DBO].[TESTA]",
								"queryTimeout": "02:00:00",
								"partitionOption": "None"
							},
							"sink": {
								"type": "AzureSqlSink",
								"writeBehavior": "insert",
								"sqlWriterUseTableLock": false
							},
							"enableStaging": false,
							"translator": {
								"type": "TabularTranslator",
								"typeConversion": true,
								"typeConversionSettings": {
									"allowDataTruncation": true,
									"treatBooleanAsNumber": false
								}
							}
						},
						"inputs": [
							{
								"referenceName": "TESTA",
								"type": "DatasetReference",
								"parameters": {}
							}
						],
						"outputs": [
							{
								"referenceName": "TESTA",
								"type": "DatasetReference",
								"parameters": {}
							}
						]
					}
				],
				"policy": {
					"elapsedTimeMetric": {},
					"cancelAfter": {}
				},
				"annotations": [],
				"lastPublishTime": "2022-08-05T04:59:48Z"
			},
			"dependsOn": []
		},
		{
			"name": "[concat(parameters('factoryName'), '/Delete_SingleFile')]",
			"type": "Microsoft.DataFactory/factories/pipelines",
			"apiVersion": "2018-06-01",
			"properties": {
				"activities": [
					{
						"name": "Delete1",
						"type": "Delete",
						"dependsOn": [],
						"policy": {
							"timeout": "7.00:00:00",
							"retry": 0,
							"retryIntervalInSeconds": 30,
							"secureOutput": false,
							"secureInput": false
						},
						"userProperties": [],
						"typeProperties": {
							"dataset": {
								"referenceName": "Delete_Dataset",
								"type": "DatasetReference",
								"parameters": {}
							},
							"logStorageSettings": {
								"linkedServiceName": {
									"referenceName": "LS_BLOB",
									"type": "LinkedServiceReference"
								},
								"path": "demo"
							},
							"enableLogging": true,
							"storeSettings": {
								"type": "AzureBlobStorageReadSettings",
								"recursive": false,
								"modifiedDatetimeStart": "2022-08-05T00:00:00.418Z",
								"enablePartitionDiscovery": false
							}
						}
					}
				],
				"policy": {
					"elapsedTimeMetric": {},
					"cancelAfter": {}
				},
				"annotations": [],
				"lastPublishTime": "2022-08-05T04:45:43Z"
			},
			"dependsOn": []
		},
		{
			"name": "[concat(parameters('factoryName'), '/Delete_multiplewildcard')]",
			"type": "Microsoft.DataFactory/factories/pipelines",
			"apiVersion": "2018-06-01",
			"properties": {
				"activities": [
					{
						"name": "Delete1",
						"type": "Delete",
						"dependsOn": [],
						"policy": {
							"timeout": "7.00:00:00",
							"retry": 0,
							"retryIntervalInSeconds": 30,
							"secureOutput": false,
							"secureInput": false
						},
						"userProperties": [],
						"typeProperties": {
							"dataset": {
								"referenceName": "DELETE_DYNAMIC",
								"type": "DatasetReference",
								"parameters": {}
							},
							"logStorageSettings": {
								"linkedServiceName": {
									"referenceName": "LS_BLOB",
									"type": "LinkedServiceReference"
								},
								"path": "demo"
							},
							"enableLogging": true,
							"storeSettings": {
								"type": "AzureBlobStorageReadSettings",
								"recursive": true,
								"wildcardFileName": "*.txt",
								"enablePartitionDiscovery": false
							}
						}
					}
				],
				"policy": {
					"elapsedTimeMetric": {},
					"cancelAfter": {}
				},
				"annotations": [],
				"lastPublishTime": "2022-08-05T04:45:43Z"
			},
			"dependsOn": []
		}
	]
}